MANIFEST.in
README.md
setup.py
plaidash/LoginForm.py
plaidash/__init__.py
plaidash/_imports_.py
plaidash/metadata.json
plaidash/package.json
plaidash/plaidash.dev.js
plaidash/plaidash.min.js
plaidash.egg-info/PKG-INFO
plaidash.egg-info/SOURCES.txt
plaidash.egg-info/dependency_links.txt
plaidash.egg-info/top_level.txt