Metadata-Version: 1.0
Name: plaidash
Version: 1.0.0
Summary: Provides Dash Components for Plaid API
Home-page: UNKNOWN
Author: Sterling Butters sterlingbutters@gmail.com
Author-email: UNKNOWN
License: GPL-3.0
Platform: UNKNOWN
